{"chunk_definitions":[{"chunk_id":"ct9wqgf3mw3px","chunk_label":"unnamed-chunk-1","document_id":"1C31694E","expansion_state":0,"options":{"engine":"r","include":false,"label":"unnamed-chunk-1","message":false,"warning":false},"row":16,"row_count":1,"visible":true},{"chunk_id":"c0k4sc9e0e8ft","chunk_label":"unnamed-chunk-5","document_id":"1C31694E","expansion_state":0,"options":{"engine":"r","label":"unnamed-chunk-6"},"row":39,"row_count":1,"visible":true},{"chunk_id":"cgcop6h6vkwep","chunk_label":"unnamed-chunk-6","document_id":"1C31694E","expansion_state":0,"options":{"engine":"r","label":"unnamed-chunk-5"},"row":44,"row_count":1,"visible":true},{"chunk_id":"cb4930723xsgr","chunk_label":"unnamed-chunk-7","document_id":"1C31694E","expansion_state":0,"options":{"echo":false,"engine":"r","label":"unnamed-chunk-6"},"row":50,"row_count":1,"visible":true},{"chunk_id":"c1wwkfwcs1wna","chunk_label":"unnamed-chunk-8","document_id":"1C31694E","expansion_state":0,"options":{"echo":false,"engine":"r","label":"unnamed-chunk-7"},"row":54,"row_count":1,"visible":true},{"chunk_id":"cf4bj77ne1e0t","chunk_label":"unnamed-chunk-9","document_id":"1C31694E","expansion_state":0,"options":{"engine":"r","label":"unnamed-chunk-8"},"row":59,"row_count":1,"visible":true},{"chunk_id":"cyhlzjyu47xc4","chunk_label":"unnamed-chunk-11","document_id":"1C31694E","expansion_state":0,"options":{"engine":"r","label":"unnamed-chunk-13"},"row":77,"row_count":1,"visible":true},{"chunk_id":"cgbh33ve97f54","chunk_label":"unnamed-chunk-13","document_id":"1C31694E","expansion_state":0,"options":{"engine":"r","label":"unnamed-chunk-3"},"row":95,"row_count":1,"visible":true},{"chunk_id":"cwvq37iuocza3","chunk_label":"unnamed-chunk-14","document_id":"1C31694E","expansion_state":0,"options":{"engine":"r","label":"unnamed-chunk-3"},"row":101,"row_count":1,"visible":true}],"doc_write_time":1520605157}